pymead/__init__.py
pymead/version.py
pymead/analysis/__init__.py
pymead/analysis/calc_aero_data.py
pymead/analysis/cfd_output_templates.py
pymead/analysis/compressible_flow.py
pymead/analysis/read_aero_data.py
pymead/analysis/single_element_inviscid.py
pymead/analysis/utils.py
pymead/core/__init__.py
pymead/core/airfoil.py
pymead/core/bezier.py
pymead/core/constraint_equations.py
pymead/core/constraint_graph.py
pymead/core/constraint_solver.py
pymead/core/constraints.py
pymead/core/control_point.py
pymead/core/dimensions.py
pymead/core/geometry_collection.py
pymead/core/line.py
pymead/core/mea.py
pymead/core/param.py
pymead/core/parametric_curve.py
pymead/core/point.py
pymead/core/pymead_obj.py
pymead/core/spline.py
pymead/core/transformation.py
pymead/core/units.py
pymead/data/__init__.py
pymead/examples/__init__.py
pymead/examples/airfoil_matching.py
pymead/examples/complex_airfoil.py
pymead/examples/high_lift.py
pymead/examples/iges_generation.py
pymead/examples/mirrored_subsection.py
pymead/examples/propulsion_airframe_integration.py
pymead/examples/simple_airfoil.py
pymead/examples/symm_airfoil.py
pymead/gui/__init__.py
pymead/gui/aero_forces_graphs.py
pymead/gui/airfoil_canvas.py
pymead/gui/airfoil_graph.py
pymead/gui/airfoil_pos_parameter.py
pymead/gui/airfoil_statistics.py
pymead/gui/analysis_graph.py
pymead/gui/autocomplete.py
pymead/gui/bounds_values_table.py
pymead/gui/concurrency.py
pymead/gui/constraint_items.py
pymead/gui/custom_context_menu_event.py
pymead/gui/custom_graphics_view.py
pymead/gui/default_settings.py
pymead/gui/dockable_tab_widget.py
pymead/gui/draggable_point.py
pymead/gui/file_selection.py
pymead/gui/gui.py
pymead/gui/help_browser.py
pymead/gui/hoverable_curve.py
pymead/gui/infty_doublespinbox.py
pymead/gui/input_dialog.py
pymead/gui/main_icon_toolbar.py
pymead/gui/message_box.py
pymead/gui/mses_settings_test.json
pymead/gui/opt_airfoil_graph.py
pymead/gui/parallel_coords_graph.py
pymead/gui/parameter_tree.py
pymead-2.0.0a26.dist-info/LICENSE.txt
pymead-2.0.0a26.dist-info/METADATA
pymead-2.0.0a26.dist-info/WHEEL
pymead-2.0.0a26.dist-info/top_level.txt
pymead-2.0.0a26.dist-info/RECORD
