Metadata-Version: 2.1
Name: pymead
Version: 2.0.0a26
Summary: Python library for generation, aerodynamic analysis, and aerodynamic shape optimization of parametric airfoils and airfoil systems
Home-page: https://github.com/mlau154/pymead
Author: Matthew G Lauer
Author-email: mlauer2015@gmail.com
License: MIT
Classifier: License :: OSI Approved :: MIT License
Classifier: Programming Language :: Python :: 3
Requires-Python: >=3.10
License-File: LICENSE.txt
Requires-Dist: scipy
Requires-Dist: numpy
Requires-Dist: shapely
Requires-Dist: matplotlib
Requires-Dist: requests >=2.31
Requires-Dist: PyQt5 ==5.15.7
Requires-Dist: pyqtgraph ==0.13.1
Requires-Dist: python-benedict
Requires-Dist: pandas
Requires-Dist: pymoo ==0.5.0
Requires-Dist: numba
Requires-Dist: PyQtWebEngine
Requires-Dist: cmcrameri
Requires-Dist: jax
Requires-Dist: jaxopt
Requires-Dist: networkx
